simAIRR/__init__.py
simAIRR/concatenate_repertoire_components/RepComponentConcatenation.py
simAIRR/concatenate_repertoire_components/__init__.py
simAIRR/config_validator/ConfigValidator.py
simAIRR/config_validator/__init__.py
simAIRR/config_validator/public_seq_pgen_count_map.tsv
simAIRR/config_validator/signal_seq_pgen_count_map.tsv
simAIRR/expand_repertoire_components/ImplantationHelper.py
simAIRR/expand_repertoire_components/PublicRepertoireGeneration.py
simAIRR/expand_repertoire_components/SignalComponentGeneration.py
simAIRR/expand_repertoire_components/__init__.py
simAIRR/olga_baseline_gen/OlgaRepertoiresGeneration.py
simAIRR/olga_baseline_gen/__init__.py
simAIRR/olga_compute_pgen/OlgaPgenComputation.py
simAIRR/olga_compute_pgen/UniqueSequenceFilter.py
simAIRR/olga_compute_pgen/__init__.py
simAIRR/pgen_count_map/PgenCountMap.py
simAIRR/pgen_count_map/__init__.py
simAIRR/sequence_presence_matrix/SequencePresenceMatrix.py
simAIRR/sequence_presence_matrix/__init__.py
simAIRR/simairr_cli/__init__.py
simAIRR/simairr_cli/simairr_cli.py
simAIRR/util/__init__.py
simAIRR/util/utilities.py
simAIRR/workflows/Workflows.py
simAIRR/workflows/__init__.py
simAIRR-0.1.dist-info/METADATA
simAIRR-0.1.dist-info/WHEEL
simAIRR-0.1.dist-info/entry_points.txt
simAIRR-0.1.dist-info/top_level.txt
simAIRR-0.1.dist-info/RECORD
