Metadata-Version: 2.1
Name: simAIRR
Version: 0.1
Summary: A tool for simulation of antigen-experienced adaptive immune receptor repertoire (AIRR) datasets for benchmarking of machine learning (ML) methods.
Home-page: 
Author: Chakravarthi Kanduri
Author-email: chakra.kanduri@gmail.com
License: MIT
